LICENSE
README.md
setup.py
heimdall_tools/__init__.py
heimdall_tools/rabbitmq.py
heimdall_tools/redis_client.py
heimdall_tools/s3.py
heimdall_tools/sns.py
heimdall_tools/sqs.py
heimdall_tools/vault.py
heimdall_tools.egg-info/PKG-INFO
heimdall_tools.egg-info/SOURCES.txt
heimdall_tools.egg-info/dependency_links.txt
heimdall_tools.egg-info/requires.txt
heimdall_tools.egg-info/top_level.txt