Metadata-Version: 2.1
Name: heimdall-tools
Version: 1.3.2
Summary: Custom package including all modules required for my application
Home-page: https://github.com/your_username/your_package
Author: Robin Thomas
Author-email: robin@clockhash.com
License: MIT
Platform: UNKNOWN
Classifier: Programming Language :: Python :: 3
Classifier: License :: OSI Approved :: MIT License
Classifier: Operating System :: OS Independent
License-File: LICENSE
